algorithm_prep/__init__.py
algorithm_prep/classic/__init__.py
algorithm_prep/classic/binary_search.py
algorithm_prep/classic/sort.py
algorithm_prep/classic/string_search.py
algorithm_prep/classic/union_find.py
test/__init__.py
test/google-datacentre.py
test/test_binary_search.py
test/test_sort.py
test/test_string_search.py
test/test_union_find.py
algorithm_prep-0.0.2.dist-info/LICENSE
algorithm_prep-0.0.2.dist-info/METADATA
algorithm_prep-0.0.2.dist-info/WHEEL
algorithm_prep-0.0.2.dist-info/top_level.txt
algorithm_prep-0.0.2.dist-info/RECORD
