Metadata-Version: 2.1
Name: algorithm-prep
Version: 0.0.2
Summary: Programming algorithm training package for programmers and students
Home-page: https://github.com/georgezlei/algorithm-training-py
Author: George Lei
Author-email: george@lei.nz
License: UNKNOWN
Platform: UNKNOWN
Classifier: Programming Language :: Python :: 3
Classifier: License :: OSI Approved :: MIT License
Classifier: Operating System :: OS Independent
Requires-Python: >=3.6
